dsabppy/__init__.py
dsabppy/dsabppy.py
dsabppy-0.0.1.dist-info/LICENSE
dsabppy-0.0.1.dist-info/METADATA
dsabppy-0.0.1.dist-info/WHEEL
dsabppy-0.0.1.dist-info/top_level.txt
dsabppy-0.0.1.dist-info/RECORD
