Metadata-Version: 2.1
Name: dsabppy
Version: 0.0.1
Summary: A small example package
Author: Bit128DS
Project-URL: Homepage, https://github.com/Dan-megabyte/dsabppy
Project-URL: Bug Tracker, https://github.com/Dan-megabyte/dsabppy/issues
Classifier: Programming Language :: Python :: 3
Classifier: License :: OSI Approved :: MIT License
Classifier: Operating System :: OS Independent
Requires-Python: >=3.7
License-File: LICENSE
